README.txt
setup.py
importio2/__init__.py
importio2/api.py
importio2/api_call.py
importio2/api_common.py
importio2/api_exception.py
importio2/apicore.py
importio2/crawl_run.py
importio2/doc_generate.py
importio2/extractor.py
importio2/extractor_data.py
importio2/extractor_util.py
importio2/jinja2_example.py
importio2/object_store.py
importio2/tocsv.py
importio2/version.py
importio2/watcher.py
importio2.egg-info/PKG-INFO
importio2.egg-info/SOURCES.txt
importio2.egg-info/dependency_links.txt
importio2.egg-info/entry_points.txt
importio2.egg-info/requires.txt
importio2.egg-info/top_level.txt
importio2/commands/__init__.py
importio2/commands/account_stats.py
importio2/commands/ad_base.py
importio2/commands/call_proc.py
importio2/commands/change_ownership.py
importio2/commands/copy_extractor.py
importio2/commands/crawl_run_download.py
importio2/commands/crawl_run_status.py
importio2/commands/create_crawl_run.py
importio2/commands/csv_download.py
importio2/commands/csv_to_crawl_run.py
importio2/commands/csv_to_db.py
importio2/commands/csv_to_json.py
importio2/commands/date_to_epoch.py
importio2/commands/download_crawl_run_data.py
importio2/commands/extractor_document_generator.py
importio2/commands/json_to_crawl_run.py
importio2/commands/run_report.py
importio2/commands/run_sql.py
importio2/commands/sql_to_csv.py
importio2/commands/upload_data.py