Metadata-Version: 1.0
Name: importio2
Version: 0.4.12
Summary: Import.io API for Python
Home-page: http://github.io/import.io/import-io-api-python
Author: David Gwartney
Author-email: david.gwartney@import.io
License: LICENSE
Platform: UNKNOWN
